vogel_model_trainer/__init__.py
vogel_model_trainer/__version__.py
vogel_model_trainer/i18n.py
vogel_model_trainer/cli/__init__.py
vogel_model_trainer/cli/main.py
vogel_model_trainer/core/__init__.py
vogel_model_trainer/core/classifier.py
vogel_model_trainer/core/deduplicator.py
vogel_model_trainer/core/evaluator.py
vogel_model_trainer/core/extractor.py
vogel_model_trainer/core/organizer.py
vogel_model_trainer/core/tester.py
vogel_model_trainer/core/trainer.py
vogel_model_trainer/utils/__init__.py
vogel_model_trainer-0.1.24.dist-info/METADATA
vogel_model_trainer-0.1.24.dist-info/WHEEL
vogel_model_trainer-0.1.24.dist-info/entry_points.txt
vogel_model_trainer-0.1.24.dist-info/licenses/LICENSE
vogel_model_trainer-0.1.24.dist-info/RECORD
