Metadata-Version: 2.4
Name: vogel-model-trainer
Version: 0.1.24
Summary: A tool to extract bird images from videos and train custom species classifiers
Project-URL: Homepage, https://github.com/kamera-linux/vogel-model-trainer
Project-URL: Repository, https://github.com/kamera-linux/vogel-model-trainer
Project-URL: Issues, https://github.com/kamera-linux/vogel-model-trainer/issues
Author-email: kamera-linux <kamera-linux@mailbox.org>
License: MIT
License-File: LICENSE
Keywords: birds,computer-vision,machine-learning,object-detection,species-classification
Classifier: Development Status :: 4 - Beta
Classifier: Intended Audience :: Developers
Classifier: Intended Audience :: Science/Research
Classifier: License :: OSI Approved :: MIT License
Classifier: Programming Language :: Python :: 3
Classifier: Programming Language :: Python :: 3.9
Classifier: Programming Language :: Python :: 3.10
Classifier: Programming Language :: Python :: 3.11
Classifier: Programming Language :: Python :: 3.12
Classifier: Topic :: Multimedia :: Video
Classifier: Topic :: Scientific/Engineering :: Artificial Intelligence
Classifier: Topic :: Scientific/Engineering :: Image Recognition
Requires-Python: >=3.9
Requires-Dist: accelerate>=0.20.0
Requires-Dist: datasets>=2.14.0
Requires-Dist: imagehash>=4.3.0
Requires-Dist: numpy>=1.24.0
Requires-Dist: opencv-python>=4.8.0
Requires-Dist: pillow>=10.0.0
Requires-Dist: rembg>=2.0.50
Requires-Dist: torch>=2.0.0
Requires-Dist: torchvision>=0.15.0
Requires-Dist: transformers>=4.30.0
Requires-Dist: ultralytics>=8.0.0
Provides-Extra: cpu
Requires-Dist: onnxruntime>=1.15.0; extra == 'cpu'
Provides-Extra: dev
Requires-Dist: black>=23.0.0; extra == 'dev'
Requires-Dist: mypy>=1.0.0; extra == 'dev'
Requires-Dist: pytest>=7.0.0; extra == 'dev'
Requires-Dist: ruff>=0.1.0; extra == 'dev'
Provides-Extra: gpu
Requires-Dist: onnxruntime-gpu>=1.15.0; extra == 'gpu'
